velocity_optimization/__init__.py
velocity_optimization/main_vp_sqp.py
velocity_optimization/interface/Receiver.py
velocity_optimization/interface/Sender.py
velocity_optimization/interface/__init__.py
velocity_optimization/opt_postproc/__init__.py
velocity_optimization/opt_postproc/main_visualize_logs.py
velocity_optimization/opt_postproc/src/CalcObjective.py
velocity_optimization/opt_postproc/src/VOptIPOPT.py
velocity_optimization/opt_postproc/src/VOptQPOASES.py
velocity_optimization/opt_postproc/src/__init__.py
velocity_optimization/opt_postproc/src/online_qp_postproc.py
velocity_optimization/opt_postproc/src/read_ltpl_raw.py
velocity_optimization/opt_postproc/vis/VisBenchmarkLogs.py
velocity_optimization/opt_postproc/vis/VisGUI.py
velocity_optimization/opt_postproc/vis/VisGlobalVals.py
velocity_optimization/opt_postproc/vis/VisObjectiveStatus.py
velocity_optimization/opt_postproc/vis/VisRuntime.py
velocity_optimization/opt_postproc/vis/__init__.py
velocity_optimization/params/interface_config.ini
velocity_optimization/params/sqp_config.ini
velocity_optimization/params/sqp_sparsity_EmergSQP50.ini
velocity_optimization/params/sqp_sparsity_PerfSQP115.ini
velocity_optimization/src/IniSQPStatemachine.py
velocity_optimization/src/SymQP.py
velocity_optimization/src/VarPower.py
velocity_optimization/src/VelQP.py
velocity_optimization/src/__init__.py
velocity_optimization/src/get_sparsity.py
velocity_optimization/src/online_qp.py
velocity_optimization/src/params_vp_sqp.py
velocity_optimization-1.3.1.dist-info/LICENSE
velocity_optimization-1.3.1.dist-info/METADATA
velocity_optimization-1.3.1.dist-info/WHEEL
velocity_optimization-1.3.1.dist-info/top_level.txt
velocity_optimization-1.3.1.dist-info/RECORD
