Metadata-Version: 2.1
Name: velocity-optimization
Version: 1.3.1
Summary: Optimizes (Maximizes) the velocity profile for a vehicle respecting physical constraints and runtime-variable input parameters.
Home-page: https://github.com/TUMFTM/velocity_optimization
Author: Thomas Herrmann
Author-email: thomas.herrmann@tum.de
License: UNKNOWN
Platform: UNKNOWN
Classifier: Programming Language :: Python :: 3
Classifier: License :: OSI Approved :: GNU Lesser General Public License v3 (LGPLv3)
Classifier: Operating System :: OS Independent
Requires-Python: >=3.5
License-File: LICENSE
Requires-Dist: numpy (>=1.18.1)
Requires-Dist: osqp (>=0.6.1)
Requires-Dist: scipy (>=1.3.3)
Requires-Dist: matplotlib (>=3.0.3)
Requires-Dist: sympy (>=1.6)
Requires-Dist: ad-interface-functions (>=0.21)
